.gitignore
COPYING.txt
README.rst
TODO.org
setup.py
examples/ci_simulation.py
examples/performance.py
examples/run_holmberg2007_sg.py
examples/simple_anf.py
examples/stats_rate_level.py
spiral_ganglion/__init__.py
spiral_ganglion/anf.py
spiral_ganglion/ci.py
spiral_ganglion/ear.py
spiral_ganglion/electrodes.py
spiral_ganglion/ih_rothman2003.mod
spiral_ganglion/k_schwarz1987.mod
spiral_ganglion/kht_rothman2003.mod
spiral_ganglion/klt_rothman2003.mod
spiral_ganglion/na_rothman1993.mod
spiral_ganglion/na_rothman2003.mod
spiral_ganglion/na_schwarz1987.mod
spiral_ganglion/noise.mod
spiral_ganglion.egg-info/PKG-INFO
spiral_ganglion.egg-info/SOURCES.txt
spiral_ganglion.egg-info/dependency_links.txt
spiral_ganglion.egg-info/requires.txt
spiral_ganglion.egg-info/top_level.txt
tests/test_geometry.py