Metadata-Version: 1.1
Name: spiral-ganglion
Version: 1
Summary: Spiral ganglion model.
Home-page: UNKNOWN
Author: Marek Rudnicki
Author-email: marek.rudnicki@tum.de
License: GPLv3+
Platform: Linux
Platform: FreeBSD
Classifier: Development Status :: 4 - Beta
Classifier: Environment :: Console
Classifier: Intended Audience :: End Users/Desktop
Classifier: Intended Audience :: Science/Research
Classifier: License :: OSI Approved :: GNU General Public License v3 or later (GPLv3+)
Classifier: Operating System :: POSIX
Classifier: Programming Language :: Python
Classifier: Programming Language :: Python :: 2.7
